matrixlibrary/__init__.py
matrixlibrary/matrix.py
matrixlibrary/vector.py
matrixlibrary-0.1.1.dist-info/licenses/LICENSE
matrixlibrary-0.1.1.dist-info/METADATA
matrixlibrary-0.1.1.dist-info/WHEEL
matrixlibrary-0.1.1.dist-info/top_level.txt
matrixlibrary-0.1.1.dist-info/RECORD
