Metadata-Version: 2.4
Name: matrixlibrary
Version: 0.1.1
Summary: A python package that provides tools to perform operations with matrices and vectors.
Author-email: Rehaan Mahmood <rehaanmd.310506@gmail.com>
License: MIT
Requires-Python: >=3.8
License-File: LICENSE
Dynamic: license-file
